logcrest/__init__.py
logcrest/config.py
logcrest/core.py
logcrest/decorator.py
logcrest/formatters.py
logcrest/handlers.py
logcrest/interfaces.py
logcrest/utils.py
logcrest-1.0.1.dist-info/METADATA
logcrest-1.0.1.dist-info/WHEEL
logcrest-1.0.1.dist-info/top_level.txt
logcrest-1.0.1.dist-info/RECORD
