Metadata-Version: 2.4
Name: logcrest
Version: 1.0.1
Summary: A production-grade, asynchronous logging decorator for Python.
Author-email: Snehangsu De <desnehangsu@gmail.com>
Project-URL: Homepage, https://github.com/snehangsude/LogCrest
Requires-Python: >=3.8
Provides-Extra: dev
Requires-Dist: pytest>=7.0.0; extra == "dev"
